dbcan/_version.py
dbcan/core.py
dbcan/main.py
dbcan/parameter.py
dbcan/IO/OverviewGenerator.py
dbcan/IO/fasta.py
dbcan/IO/gff.py
dbcan/annotation/CGCFinder.py
dbcan/annotation/cgc_substrate_prediction.py
dbcan/annotation/diamond.py
dbcan/annotation/pyhmmer_search.py
dbcan/annotation/signalp_tmhmm.py
dbcan/configs/base_config.py
dbcan/configs/cgc_substrate_config.py
dbcan/configs/cgcfinder_config.py
dbcan/configs/database_config.py
dbcan/configs/diamond_config.py
dbcan/configs/diamond_unassembly_config.py
dbcan/configs/plots_config.py
dbcan/configs/pyhmmer_config.py
dbcan/configs/signalp_tmhmm_config.py
dbcan/configs/utils_config.py
dbcan/constants/OverviewGenerator_constants.py
dbcan/constants/base_constants.py
dbcan/constants/cgc_substrate_prediction_constants.py
dbcan/constants/cgcfinder_constants.py
dbcan/constants/databases_constants.py
dbcan/constants/diamond_constants.py
dbcan/constants/gff_constants.py
dbcan/constants/plot_cgc_circle_constants.py
dbcan/constants/plots_constants.py
dbcan/constants/process_dbcan_sub_constants.py
dbcan/constants/process_utils_constants.py
dbcan/constants/pyhmmer_search_constants.py
dbcan/constants/signalp_tmhmm_constants.py
dbcan/constants/utils_constants.py
dbcan/plot/plot_cgc_circle.py
dbcan/plot/syntenic_plot.py
dbcan/process/process_dbcan_sub.py
dbcan/process/process_utils.py
dbcan/utils/__init__.py
dbcan/utils/database.py
dbcan/utils/diamond_unassembly.py
dbcan/utils/memory_monitor.py
dbcan/utils/plots.py
dbcan/utils/utils.py
dbcan-5.2.6.dist-info/METADATA
dbcan-5.2.6.dist-info/WHEEL
dbcan-5.2.6.dist-info/entry_points.txt
dbcan-5.2.6.dist-info/licenses/LICENSE
dbcan-5.2.6.dist-info/RECORD
