Metadata-Version: 2.4
Name: dbcan
Version: 5.2.6
Summary: updated standalone version of dbCAN annotation tool for automated CAZyme annotation
Project-URL: Documentation, https://run-dbcan-new.readthedocs.io/en/latest/
Project-URL: Source, https://github.com/bcb-unl/run_dbcan_new/
Project-URL: Home-page, https://bcb.unl.edu/dbCAN2/
Author: Xinpeng Zhang, Haidong Yi, Le Huang, Jinfang Zheng, Qiwei Ge, Tanner Yohe
Maintainer-email: Xinpeng Zhang <xzhang55@huskers.unl.edu>, Le Huang <lehuang@unc.edu>, Haidong Yi <haidyi@cs.unc.edu>
License:                     GNU GENERAL PUBLIC LICENSE
License-File: LICENSE
Classifier: Development Status :: 4 - Beta
Classifier: Environment :: Console
Classifier: Intended Audience :: Science/Research
Classifier: License :: OSI Approved :: GNU General Public License v3 (GPLv3)
Classifier: Operating System :: POSIX :: Linux
Classifier: Programming Language :: Python :: 3
Classifier: Topic :: Scientific/Engineering :: Bio-Informatics
Requires-Python: >=3.10
Requires-Dist: bcbio-gff==0.7.1
Requires-Dist: biopython==1.85
Requires-Dist: importlib-metadata; python_version < '3.13'
Requires-Dist: matplotlib==3.10.1
Requires-Dist: openpyxl==3.1.5
Requires-Dist: pandas==2.2.3
Requires-Dist: psutil~=6.0
Requires-Dist: pycirclize==1.9.0
Requires-Dist: pyhmmer==0.11.0
Requires-Dist: pyrodigal==3.6.3
Requires-Dist: pysam==0.23.0
Requires-Dist: requests==2.32.3
Requires-Dist: rich-click==1.8.8
Requires-Dist: seaborn==0.13.2
Requires-Dist: session-info
Requires-Dist: tqdm==4.67.1
Provides-Extra: dev
Requires-Dist: pkginfo>=1.10.0; extra == 'dev'
Requires-Dist: pre-commit; extra == 'dev'
Requires-Dist: setuptools-scm<8,>7; extra == 'dev'
Requires-Dist: twine>=6.1.0; extra == 'dev'
Provides-Extra: doc
Requires-Dist: docutils!=0.18.*,!=0.19.*,>=0.8; extra == 'doc'
Requires-Dist: ipykernel; extra == 'doc'
Requires-Dist: ipython; extra == 'doc'
Requires-Dist: myst-nb; extra == 'doc'
Requires-Dist: sphinx-argparse; extra == 'doc'
Requires-Dist: sphinx-autodoc-typehints; extra == 'doc'
Requires-Dist: sphinx-book-theme>=1.0.0; extra == 'doc'
Requires-Dist: sphinx-click; extra == 'doc'
Requires-Dist: sphinx-copybutton; extra == 'doc'
Requires-Dist: sphinx-design; extra == 'doc'
Requires-Dist: sphinx-issues; extra == 'doc'
Requires-Dist: sphinx-rtd-theme; extra == 'doc'
Requires-Dist: sphinx>=4; extra == 'doc'
Requires-Dist: sphinxcontrib-bibtex>=1.0.0; extra == 'doc'
Requires-Dist: sphinxext-opengraph; extra == 'doc'
Provides-Extra: test
Requires-Dist: coverage; extra == 'test'
Requires-Dist: pytest; extra == 'test'
Requires-Dist: pytest-cov; extra == 'test'
Requires-Dist: pytest-html; extra == 'test'
Requires-Dist: pytest-xdist; extra == 'test'
